pycronie/__init__.py
pycronie/cronie.py
pycronie-0.3.0.dist-info/LICENSE.md
pycronie-0.3.0.dist-info/METADATA
pycronie-0.3.0.dist-info/WHEEL
pycronie-0.3.0.dist-info/RECORD
