Metadata-Version: 2.3
Name: pycronie
Version: 0.3.0
Summary: A project to manage cron jobs.
License: MIT
Keywords: cron,scheduler,parser
Author: Robin Lösch
Author-email: robin@chilio.net
Requires-Python: >=3.9,<4.0
Classifier: Development Status :: 4 - Beta
Classifier: License :: OSI Approved :: MIT License
Classifier: Operating System :: OS Independent
Classifier: Programming Language :: Python :: 3
Classifier: Programming Language :: Python :: 3.9
Classifier: Programming Language :: Python :: 3.10
Classifier: Programming Language :: Python :: 3.11
Classifier: Programming Language :: Python :: 3.12
Classifier: Programming Language :: Python :: 3.13
Project-URL: Repository, https://github.com/crest42/pycronie
